battlemetrics/__init__.py
battlemetrics/client.py
battlemetrics/errors.py
battlemetrics/http.py
battlemetrics/models/__init__.py
battlemetrics/models/ban.py
battlemetrics/models/banlist.py
battlemetrics/models/base.py
battlemetrics/models/flag.py
battlemetrics/models/game.py
battlemetrics/models/misc.py
battlemetrics/models/note.py
battlemetrics/models/organization.py
battlemetrics/models/player.py
battlemetrics/models/query.py
battlemetrics/models/server.py
battlemetrics/models/session.py
battlemetrics/models/user.py
battlemetrics-2.0.4.dist-info/METADATA
battlemetrics-2.0.4.dist-info/WHEEL
battlemetrics-2.0.4.dist-info/licenses/LICENSE
battlemetrics-2.0.4.dist-info/RECORD
