Metadata-Version: 2.4
Name: battlemetrics
Version: 2.0.4
Summary: Asyncronous Python wrapper for the BattleMetrics API.
Project-URL: Homepage, https://github.com/OseSem/battlemetrics
Project-URL: Issue Tracker, https://github.com/OseSem/battlemetrics/issues
Author-email: OseSem <sem@osesem.xyz>, Gnomeslayer <declan.otten@live.com.au>
License: MIT
License-File: LICENSE
Classifier: Development Status :: 5 - Production/Stable
Classifier: Intended Audience :: Developers
Classifier: License :: OSI Approved :: MIT License
Classifier: Programming Language :: Python :: 3
Classifier: Programming Language :: Python :: 3.12
Classifier: Programming Language :: Python :: 3.13
Requires-Python: >=3.12
Requires-Dist: aiohttp>=3.9.3
Requires-Dist: pydantic>=2.0.0
